llm_mediator/__init__.py
llm_mediator/cache.py
llm_mediator/embedding.py
llm_mediator/folders.py
llm_mediator/formatter.py
llm_mediator/gpt.py
llm_mediator/llm.py
llm_mediator/parallel_tasks_queuer.py
LLM_Mediator-0.9.17.dist-info/LICENSE
LLM_Mediator-0.9.17.dist-info/METADATA
LLM_Mediator-0.9.17.dist-info/WHEEL
LLM_Mediator-0.9.17.dist-info/top_level.txt
LLM_Mediator-0.9.17.dist-info/RECORD
