Metadata-Version: 2.1
Name: LLM-Mediator
Version: 0.9.17
Summary: Just a simple mediator for different LLM models.
Home-page: https://github.com/zeuscsc/llm_mediator.git
Author: Zeus Chiu
Author-email: zeuscsc@gmail.com
License: MIT
Classifier: License :: OSI Approved :: MIT License
Classifier: Programming Language :: Python
Classifier: Programming Language :: Python :: 3
Classifier: Programming Language :: Python :: 3.6
Classifier: Programming Language :: Python :: Implementation :: CPython
Classifier: Programming Language :: Python :: Implementation :: PyPy
Requires-Python: >=3.9.0
License-File: LICENSE
Requires-Dist: openai
Requires-Dist: pynvml
